django_sram/__init__.py
django_sram/_version.py
django_sram/admin.py
django_sram/apps.py
django_sram/authentication.py
django_sram/entitlements.py
django_sram/models.py
django_sram/token.py
django_sram/urls.py
django_sram/user.py
django_sram/migrations/__init__.py
django_sram/views/__init__.py
django_sram/views/userinfo_viewset.py
django_sram-0.1.2.dist-info/licenses/LICENSE
django_sram-0.1.2.dist-info/METADATA
django_sram-0.1.2.dist-info/WHEEL
django_sram-0.1.2.dist-info/top_level.txt
django_sram-0.1.2.dist-info/RECORD
