Metadata-Version: 2.4
Name: django_sram
Version: 0.1.2
Summary: SURF Research Access Management integration for Django
Home-page: https://gitlab.com/astron-sdc/django_sram/
Maintainer-email: "K.Y. Kliffen" <kliffen@astron.nl>, "M. Altena" <altena@astron.nl>
Project-URL: Homepage, https://gitlab.com/astron-sdc/django_sram/
Project-URL: Issues, https://gitlab.com/astron-sdc/django_sram/-/issues
Classifier: Programming Language :: Python :: 3
Classifier: License :: OSI Approved :: Apache Software License
Classifier: Operating System :: OS Independent
Classifier: Framework :: Django
Classifier: Intended Audience :: Science/Research
Classifier: Topic :: Scientific/Engineering :: Astronomy
Requires-Python: >=3.10
License-File: LICENSE
Requires-Dist: django>=5
Requires-Dist: djangorestframework>=3.16
Requires-Dist: djangorestframework-simplejwt[crypto]>=5.5
Dynamic: license-file
